feedcrawler/__init__.py
feedcrawler/run.py
feedcrawler/external_sites/__init__.py
feedcrawler/external_sites/captcha/__init__.py
feedcrawler/external_sites/captcha/filecrypt.py
feedcrawler/external_sites/feed_search/__init__.py
feedcrawler/external_sites/feed_search/content_all.py
feedcrawler/external_sites/feed_search/content_shows.py
feedcrawler/external_sites/feed_search/shared.py
feedcrawler/external_sites/feed_search/sites/__init__.py
feedcrawler/external_sites/feed_search/sites/content_all_by.py
feedcrawler/external_sites/feed_search/sites/content_all_dw.py
feedcrawler/external_sites/feed_search/sites/content_all_ff.py
feedcrawler/external_sites/feed_search/sites/content_all_fx.py
feedcrawler/external_sites/feed_search/sites/content_all_hw.py
feedcrawler/external_sites/feed_search/sites/content_all_nk.py
feedcrawler/external_sites/feed_search/sites/content_all_nx.py
feedcrawler/external_sites/feed_search/sites/content_all_ww.py
feedcrawler/external_sites/feed_search/sites/content_custom_dd.py
feedcrawler/external_sites/feed_search/sites/content_shows_dj.py
feedcrawler/external_sites/feed_search/sites/content_shows_sf.py
feedcrawler/external_sites/feed_search/sites/content_shows_sj.py
feedcrawler/external_sites/metadata/__init__.py
feedcrawler/external_sites/metadata/imdb.py
feedcrawler/external_sites/web_search/__init__.py
feedcrawler/external_sites/web_search/content_all.py
feedcrawler/external_sites/web_search/content_shows.py
feedcrawler/external_sites/web_search/shared.py
feedcrawler/external_sites/web_search/sites/__init__.py
feedcrawler/external_sites/web_search/sites/content_all_by.py
feedcrawler/external_sites/web_search/sites/content_all_dw.py
feedcrawler/external_sites/web_search/sites/content_all_fx.py
feedcrawler/external_sites/web_search/sites/content_all_hw.py
feedcrawler/external_sites/web_search/sites/content_all_nk.py
feedcrawler/external_sites/web_search/sites/content_all_nx.py
feedcrawler/external_tools/__init__.py
feedcrawler-21.0.8.dist-info/LICENSE.md
feedcrawler-21.0.8.dist-info/METADATA
feedcrawler-21.0.8.dist-info/WHEEL
feedcrawler-21.0.8.dist-info/entry_points.txt
feedcrawler-21.0.8.dist-info/top_level.txt
feedcrawler-21.0.8.dist-info/RECORD
