Metadata-Version: 2.1
Name: feedcrawler
Version: 21.0.8
Summary: Automate downloads using predefined sites and the My-JDownloader-API
Home-page: https://github.com/rix1337/FeedCrawler
Author: rix1337
Author-email: 
Classifier: Programming Language :: Python :: 3
Classifier: License :: OSI Approved :: MIT License
Classifier: Operating System :: OS Independent
License-File: LICENSE.md
Requires-Dist: beautifulsoup4 ==4.12.3
Requires-Dist: bottle ==0.13.2
Requires-Dist: dukpy ==0.5.0
Requires-Dist: pycryptodomex ==3.21.0
Requires-Dist: pystray ==0.19.5
